av1clip/__init__.py
av1clip/av1clip.py
av1clip-0.1.1.dist-info/LICENSE
av1clip-0.1.1.dist-info/METADATA
av1clip-0.1.1.dist-info/WHEEL
av1clip-0.1.1.dist-info/entry_points.txt
av1clip-0.1.1.dist-info/top_level.txt
av1clip-0.1.1.dist-info/RECORD
