Metadata-Version: 2.1
Name: av1clip
Version: 0.1.1
Summary: A cli script to create .webm clips using mpv, svt-av1 and ffmpeg
Home-page: https://github.com/lmaonator/av1clip
Author: lmaonator
Author-email: lmaonator@gmail.com
License: UNKNOWN
Project-URL: Bug Tracker, https://github.com/lmaonator/av1clip/issues
Platform: UNKNOWN
Classifier: Development Status :: 4 - Beta
Classifier: Programming Language :: Python :: 3
Classifier: License :: OSI Approved :: GNU General Public License v3 (GPLv3)
Classifier: Operating System :: OS Independent
Classifier: Environment :: Console
Classifier: Natural Language :: English
Classifier: Topic :: Multimedia :: Video :: Conversion
Classifier: Topic :: Utilities
Requires-Python: >=3.9
License-File: LICENSE
